README.md
pyproject.toml
setup.cfg
setup.py
src/smsiran/__init__.py
src/smsiran/ghasedak.py
src/smsiran/sms_ir.py
src/smsiran.egg-info/PKG-INFO
src/smsiran.egg-info/SOURCES.txt
src/smsiran.egg-info/dependency_links.txt
src/smsiran.egg-info/requires.txt
src/smsiran.egg-info/top_level.txt
src/smsiran/tests/__init__.py
src/smsiran/tests/test_sms_ir.py