Metadata-Version: 2.1
Name: smsiran
Version: 0.0.5
Summary: A library for using SMS web services in IRAN
Home-page: https://github.com/avanditc/smsiran
Author: Soroush piri zendedel
Author-email: soroush_zendedel@live.com
License: MIT
Download-URL: https://github.com/avanditc/smsiran/archive/refs/tags/v0.0.5.tar.gz
Project-URL: Bug Tracker, https://github.com/avanditc/smsiran/issues
Project-URL: Owner, https://AvandITC.ir
Keywords: SMS,Persian,iran,web service,sms web service
Platform: UNKNOWN
Classifier: Development Status :: 1 - Planning
Classifier: Intended Audience :: Developers
Classifier: Programming Language :: Python :: 3
Classifier: License :: OSI Approved :: MIT License
Classifier: Operating System :: OS Independent
Requires-Python: >=3.6
